pyrpc/__init__.py
python_rpc-0.329.2.dist-info/DESCRIPTION.rst
python_rpc-0.329.2.dist-info/METADATA
python_rpc-0.329.2.dist-info/RECORD
python_rpc-0.329.2.dist-info/WHEEL
python_rpc-0.329.2.dist-info/metadata.json
python_rpc-0.329.2.dist-info/top_level.txt
