Metadata-Version: 2.0
Name: python-rpc
Version: 0.329.2
Summary: Python only RPC library based on ZeroMQ and Pickle
Home-page: https://github.com/hholst80/python-rpc
Author: Henrik Holst
Author-email: hholst80@gmail.com
License: The Unlicense
Platform: UNKNOWN
Requires-Dist: pyzmq
